thebrian/__init__.py
thebrian/file.py
thebrian/stream.py
thebrian/utils.py
thebrian-2025.3.1.dist-info/LICENSE
thebrian-2025.3.1.dist-info/METADATA
thebrian-2025.3.1.dist-info/WHEEL
thebrian-2025.3.1.dist-info/RECORD
