Metadata-Version: 2.1
Name: thebrian
Version: 2025.3.1
Summary: mcap utils
Home-page: https://pypi.org/project/thebrian/
License: MIT
Keywords: mcap
Author: walchko
Author-email: walchko@users.noreply.github.com
Requires-Python: >=3.9
Classifier: Development Status :: 4 - Beta
Classifier: Intended Audience :: Developers
Classifier: License :: OSI Approved :: MIT License
Classifier: Operating System :: OS Independent
Classifier: Programming Language :: Python :: 3
Classifier: Programming Language :: Python :: 3.9
Classifier: Programming Language :: Python :: 3.10
Classifier: Programming Language :: Python :: 3.11
Classifier: Programming Language :: Python :: 3.12
Classifier: Programming Language :: Python :: 3.13
Classifier: Topic :: Software Development :: Libraries
Classifier: Topic :: Software Development :: Libraries :: Application Frameworks
Classifier: Topic :: Software Development :: Libraries :: Python Modules
Requires-Dist: foxglove-schemas-protobuf
Requires-Dist: foxglove-websocket[examples]
Requires-Dist: mcap
Requires-Dist: mcap-protobuf-support
Requires-Dist: protobuf
Project-URL: Repository, http://github.com/MomsFriendlyRobotCompany/mcap-protobuf
